setup.cfg
setup.py
bthomehub/__init__.py
bthomehub/bthomeclient.py
bthomehub/exception.py
bthomehub_client.egg-info/PKG-INFO
bthomehub_client.egg-info/SOURCES.txt
bthomehub_client.egg-info/dependency_links.txt
bthomehub_client.egg-info/not-zip-safe
bthomehub_client.egg-info/requires.txt
bthomehub_client.egg-info/top_level.txt