Metadata-Version: 1.1
Name: bthomehub-client
Version: 0.1
Summary: A Python client that can interact with BT Home Hub routers.
Home-page: https://github.com/onegambler/bthomehub_client
Author: oneGambler
Author-email: UNKNOWN
License: MIT
Download-URL: https://github.com/onegambler/bthomehub_client/archive/1.0.tar.gz
Platform: UNKNOWN
